Design/alu.v
/*--------------------------------------------------------------------------
    File Name :alu.v
    File Description :
    Project Name :
    Author Name : abhaysinh chavda
    Creation Date : 13-01-2020
    Last Modified : Thursday 19 March 2020 09:29:39 AM IST
    Version :
    Organization : eitra        
--------------------------------------------------------------------------*/
`timescale 10ns/10ns

module alu(
  output reg [15:0] result,
	output reg [4:0] flags,
	input [15:0] operand1,operand2,
	input [5:0] opcode);

	reg [15:0] temp;

	initial flags = 5'b00000;//[SZNVC] 
	
  always @(*)
	begin
		flags = 5'b00000; //[SZNVC]
		case(opcode)
			6'b001_001,6'b010_001: //ADD,ADDi
				begin
          if(operand1[15] == 1'b0 && operand2[15] == 1'b0) //ADDITION OF TWO POSITIVE NUMBERS  OR  TWO UNSIGNED NUMBERS
          begin
							result = operand1 + operand2;		
              if(result[15] == 1'b1) //OVERFLOW OCCURED 
								flags[1] = 1'b1;
          end
            
          else if((operand1[15] == 1'b0 && operand2[15] == 1'b1) || (operand1[15] == 1'b1 && operand2[15] == 1'b0)) //ADDITION OF POSITIVE AND NEGATIVE NUMBER  OR  TWO UNSINGED NUMBERS
					begin
							{flags[0],result} = operand1 + operand2; //CARRY FLAG OCCURED
							flags[4] = result[15];
					end
            
          else if(operand1[15] == 1'b1 && operand2[15] == 1'b1) //ADDITION TWO NEGATIVE NUMBERS  OR  TWO SIGNED NUMBERS
					begin
							{flags[0],result} = operand1 + operand2; //CARRY FLAG OCCURED
							flags[4] = 1'b1;
              if(result[15] == 1'b0)   //OVERFLOW OCCURED
								flags[1] = 1'b1;
	
						end
				end
		
			6'b001_111: //MUL
				begin
          {flags[0],result} = operand1 * operand2;
				end
				
			6'b001_010,6'b010_010,6'b001_110,6'b010_110: //SUB, SUBi, CMP, CMPi
				begin
					temp = (~operand2 + 1'b1);

					if(operand1[15] == 1'b0 && temp[15] == 1'b0) //ADDITION OF TWO POSITIVE NUMBERS  OR  TWO UNSIGNED NUMBERS
						begin
							result = operand1 + temp;
              if(result[15] == 1'b1) //OVERFLOW OCCURED 
								flags[1] = 1'b1;
            end
					
          else if((operand1[15] == 1'b0 && temp[15] == 1'b1) || (operand1[15] == 1'b1 && temp[15] == 1'b0)) //ADDITION OF POSITIVE AND NEGATIVE NUMBER  OR  ONE UNSINGED AND ONE SIGNED NUMBERS
          begin
							{flags[0],result} = operand1 + temp;
							flags[4] = result[15];
          end
					
          else if(operand1[15] == 1'b1 && temp[15] == 1'b1) //ADDITION TWO NEGATIVE NUMBERS  OR  TWO SIGNED NUMBERS
					begin
							{flags[0],result} = operand1 + temp;
							flags[4] = 1'b1;
							if(result[15] == 1'b0) //OVERFLOW OCCURED
								flags[1] = 1'b1;
          end


				end


			6'b001_011,010_011: //XOR,XORi
				begin
					result = operand1 ^ operand2;
					flags[4] = result[15];	
				end
			
      6'b001_100,010_100: //AND,ANDi
				begin
					result = operand1 & operand2;	
					flags[4] = result[15];	
        end
			
      6'b001_101,010_101: //OR,ORi
				begin
					result = operand1 | operand2;	
					flags[4] = result[15];	
				end

			6'b011_001: //COM
				begin
					result = ~operand1;
					flags[4] = result[15];
        end

			6'b011_000: //NEG
				begin
					result = ~operand1 + 1'b1;
					flags[4] = result[15];
        end

			6'b011_010: //SRL
				begin
					flags[0] = operand1[0];
					result = operand1 >> 1;
					flags[4] = result[15];	
				end

			6'b011_011: //SLL
				begin
					flags[0] = operand1[15];
					result = operand1 << 1;
					flags[4] = result[15];	
				end

			6'b011_110: //ASR
				begin
					result = operand1 >>> 1;
					flags[4] = result[15];	
				end

			6'b011_111: //CLR
				begin
					result = {16{1'b0}};
				end

			6'b011_101: //INC
				begin
          if(operand1[15] == 1'b0) 
          begin
							result = operand1 + 1;		

							if(result[15] == 1'b1) //OVERFLOW OCCURED 
								flags[1] = 1'b1;
	
					end

					else if(operand1[15] == 1'b1) 
					begin
							{flags[0],result} = operand1 + 1;
							flags[4] = result[15];
							
              if(result[15] == 1'b0) //OVERFLOW OCCURED
								flags[1] = 1'b1;
          end
        end

			6'b011_100: //DEC
				begin

					if(operand1[15] == 1'b0)  
						begin
							{flags[0],result} = operand1 + {16{1'b1}};	
							flags[4] = result[15];	
            end

					else if(operand1[15] == 1'b1) 
						begin
							{flags[0],result} = operand1 + {16{1'b1}};
							flags[4] = 1'b1;
							if(result[15] == 1'b0) //OVERFLOW OCCURED
								flags[1] = 1'b1;
            end


				end
		endcase
    
    if(result == 0)  //CHECK FOR ZERO FLAG
      flags[3] = 1'b1;
    if(result[15] == 1'b1)  //NEGATIVE NUMBER CHECK
			flags[2] = 1'b1;

		end	
	
endmodule

Test_Bench/alu_tb.v
/*--------------------------------------------------------------------------
    File Name :alu_tb.v
    File Description :
    Project Name :
    Author Name : abhaysinh chavda
    Creation Date : 18-03-2020
    Last Modified : Thursday 19 March 2020 09:30:31 AM IST
    Version :
    Organization : eitra        
--------------------------------------------------------------------------*/
`timescale 10ns/10ns

module alu_tb();
wire [15:0]result;
wire [4:0]flags;
reg [15:0]operand1,operand2;
reg [5:0]opcode;

alu m(.result,.flags,.operand1,.operand2,.opcode);

initial begin
  $dumpfile("alu.vcd");
  $dumpvars;
  $monitor("opcode=%b operand1=%b operand2=%b flags=%b result=%b",opcode,operand1,operand2,flags,result);

  operand1<=16'b0000_1111_1111_1111;operand2<=16'b0001_1111_1111_0000;

  #10 opcode<=6'b001_001;  // ADD
  #10 opcode<=6'b010_001;  // ADDi
  
  #10 opcode<=6'b001_111;  // MUL
  
  #10 opcode<=6'b001_010;  // SUB
  #10 opcode<=6'b010_010;  // SUBi
  #10 opcode<=6'b001_110;  // CMP
  #10 opcode<=6'b010_110;  // CMPi
  
  #10 opcode<=6'b001_011;  // XOR
  #10 opcode<=6'b010_011;  // XORi
  
  #10 opcode<=6'b001_100;  // AND
  #10 opcode<=6'b010_100;  // ANDi
  
  #10 opcode<=6'b001_101;  // OR
  #10 opcode<=6'b010_101;  // ORi

  #10 opcode<=6'b011_001; // COM
  #10 opcode<=6'b011_000; // NEG
  #10 opcode<=6'b011_010; // SRL
  #10 opcode<=6'b011_011; // SLL
  #10 opcode<=6'b011_110; // ASR
  
  #10 opcode<=6'b011_111;  // CLR
  #10 opcode<=6'b011_101;  // INC
  #10 opcode<=6'b011_100;  // DEC

  #10 operand1<=16'b1000_1111_1111_1111;operand2<=16'b0001_1111_1111_0000;
  
  #10 opcode<=6'b001_001;  // ADD
  #10 opcode<=6'b010_001;  // ADDi
  
  #10 opcode<=6'b001_111;  // MUL
  
  #10 opcode<=6'b001_010;  // SUB
  #10 opcode<=6'b010_010;  // SUBi
  #10 opcode<=6'b001_110;  // CMP
  #10 opcode<=6'b010_110;  // CMPi
  
  #10 opcode<=6'b001_011;  // XOR
  #10 opcode<=6'b010_011;  // XORi
  
  #10 opcode<=6'b001_100;  // AND
  #10 opcode<=6'b010_100;  // ANDi
  
  #10 opcode<=6'b001_101;  // OR
  #10 opcode<=6'b010_101;  // ORi

  #10 opcode<=6'b011_001; // COM
  #10 opcode<=6'b011_000; // NEG
  #10 opcode<=6'b011_010; // SRL
  #10 opcode<=6'b011_011; // SLL
  #10 opcode<=6'b011_110; // ASR
  
  #10 opcode<=6'b011_111;  // CLR
  #10 opcode<=6'b011_101;  // INC
  #10 opcode<=6'b011_100;  // DEC
  
  #10 operand1<=16'b0000_1111_1111_1111;operand2<=16'b1001_1111_1111_0000;
  
  #10 opcode<=6'b001_001;  // ADD
  #10 opcode<=6'b010_001;  // ADDi
  
  #10 opcode<=6'b001_111;  // MUL
  
  #10 opcode<=6'b001_010;  // SUB
  #10 opcode<=6'b010_010;  // SUBi
  #10 opcode<=6'b001_110;  // CMP
  #10 opcode<=6'b010_110;  // CMPi
  
  #10 opcode<=6'b001_011;  // XOR
  #10 opcode<=6'b010_011;  // XORi
  
  #10 opcode<=6'b001_100;  // AND
  #10 opcode<=6'b010_100;  // ANDi
  
  #10 opcode<=6'b001_101;  // OR
  #10 opcode<=6'b010_101;  // ORi

  #10 opcode<=6'b011_001; // COM
  #10 opcode<=6'b011_000; // NEG
  #10 opcode<=6'b011_010; // SRL
  #10 opcode<=6'b011_011; // SLL
  #10 opcode<=6'b011_110; // ASR
  
  #10 opcode<=6'b011_111;  // CLR
  #10 opcode<=6'b011_101;  // INC
  #10 opcode<=6'b011_100;  // DEC
 
  #10 operand1<=16'b1000_1111_1111_1111;operand2<=16'b1001_1111_1111_0000;
  
  #10 opcode<=6'b001_001;  // ADD
  #10 opcode<=6'b010_001;  // ADDi
  
  #10 opcode<=6'b001_111;  // MUL
  
  #10 opcode<=6'b001_010;  // SUB
  #10 opcode<=6'b010_010;  // SUBi
  #10 opcode<=6'b001_110;  // CMP
  #10 opcode<=6'b010_110;  // CMPi
  
  #10 opcode<=6'b001_011;  // XOR
  #10 opcode<=6'b010_011;  // XORi
  
  #10 opcode<=6'b001_100;  // AND
  #10 opcode<=6'b010_100;  // ANDi
  
  #10 opcode<=6'b001_101;  // OR
  #10 opcode<=6'b010_101;  // ORi

  #10 opcode<=6'b011_001; // COM
  #10 opcode<=6'b011_000; // NEG
  #10 opcode<=6'b011_010; // SRL
  #10 opcode<=6'b011_011; // SLL
  #10 opcode<=6'b011_110; // ASR
  
  #10 opcode<=6'b011_111;  // CLR
  #10 opcode<=6'b011_101;  // INC
  #10 opcode<=6'b011_100;  // DEC

  #10 $finish;
  end

endmodule

Simulation/alu.vcd
$date
	Thu Mar 19 09:30:38 2020
$end
$version
	Icarus Verilog
$end
$timescale
	10ns
$end
$scope module alu_tb $end
$var wire 16 ! result [15:0] $end
$var wire 5 " flags [4:0] $end
$var reg 6 # opcode [5:0] $end
$var reg 16 $ operand1 [15:0] $end
$var reg 16 % operand2 [15:0] $end
$scope module m $end
$var wire 6 & opcode [5:0] $end
$var wire 16 ' operand1 [15:0] $end
$var wire 16 ( operand2 [15:0] $end
$var reg 5 ) flags [4:0] $end
$var reg 16 * result [15:0] $end
$var reg 16 + temp [15:0] $end
$upscope $end
$upscope $end
$enddefinitions $end
#0
$dumpvars
bx +
bx *
b0 )
b1111111110000 (
b111111111111 '
bx &
b1111111110000 %
b111111111111 $
bx #
b0 "
bx !
$end
#10
b10111111101111 !
b10111111101111 *
b1001 #
b1001 &
#20
b10001 #
b10001 &
#30
b100 "
b100 )
b1110000000010000 !
b1110000000010000 *
b1111 #
b1111 &
#40
b1111000000001111 !
b1111000000001111 *
b1110000000010000 +
b10100 "
b10100 )
b1010 #
b1010 &
#50
b10100 "
b10100 )
b10010 #
b10010 &
#60
b10100 "
b10100 )
b1110 #
b1110 &
#70
b10100 "
b10100 )
b10110 #
b10110 &
#80
b1000000001111 !
b1000000001111 *
b0 "
b0 )
b1011 #
b1011 &
#90
b10011 #
b10011 &
#100
b111111110000 !
b111111110000 *
b1100 #
b1100 &
#110
b10100 #
b10100 &
#120
b1111111111111 !
b1111111111111 *
b1101 #
b1101 &
#130
b10101 #
b10101 &
#140
b10100 "
b10100 )
b1111000000000000 !
b1111000000000000 *
b11001 #
b11001 &
#150
b1111000000000001 !
b1111000000000001 *
b10100 "
b10100 )
b11000 #
b11000 &
#160
b11111111111 !
b11111111111 *
b1 "
b1 )
b11010 #
b11010 &
#170
b1111111111110 !
b1111111111110 *
b0 "
b0 )
b11011 #
b11011 &
#180
b11111111111 !
b11111111111 *
b11110 #
b11110 &
#190
b1000 "
b1000 )
b0 !
b0 *
b11111 #
b11111 &
#200
b1000000000000 !
b1000000000000 *
b0 "
b0 )
b11101 #
b11101 &
#210
b1 "
b1 )
b111111111110 !
b111111111110 *
b11100 #
b11100 &
#220
b1000111111111110 !
b1000111111111110 *
b10101 "
b10101 )
b1000111111111111 $
b1000111111111111 '
#230
b1010111111101111 !
b1010111111101111 *
b10100 "
b10100 )
b1001 #
b1001 &
#240
b10100 "
b10100 )
b10001 #
b10001 &
#250
b1110000000010000 !
b1110000000010000 *
b100 "
b100 )
b1111 #
b1111 &
#260
b111000000001111 !
b111000000001111 *
b10011 "
b10011 )
b1010 #
b1010 &
#270
b10011 "
b10011 )
b10010 #
b10010 &
#280
b10011 "
b10011 )
b1110 #
b1110 &
#290
b10011 "
b10011 )
b10110 #
b10110 &
#300
b1001000000001111 !
b1001000000001111 *
b10100 "
b10100 )
b1011 #
b1011 &
#310
b100 "
b100 )
b10011 #
b10011 &
#320
b111111110000 !
b111111110000 *
b0 "
b0 )
b1100 #
b1100 &
#330
b10100 #
b10100 &
#340
b10100 "
b10100 )
b1001111111111111 !
b1001111111111111 *
b1101 #
b1101 &
#350
b100 "
b100 )
b10101 #
b10101 &
#360
b111000000000000 !
b111000000000000 *
b0 "
b0 )
b11001 #
b11001 &
#370
b111000000000001 !
b111000000000001 *
b11000 #
b11000 &
#380
b100011111111111 !
b100011111111111 *
b1 "
b1 )
b11010 #
b11010 &
#390
b1111111111110 !
b1111111111110 *
b1 "
b1 )
b11011 #
b11011 &
#400
b100011111111111 !
b100011111111111 *
b0 "
b0 )
b11110 #
b11110 &
#410
b1000 "
b1000 )
b0 !
b0 *
b11111 #
b11111 &
#420
b1001000000000000 !
b1001000000000000 *
b10100 "
b10100 )
b11101 #
b11101 &
#430
b1000111111111110 !
b1000111111111110 *
b10101 "
b10101 )
b11100 #
b11100 &
#440
b111111111110 !
b111111111110 *
b1 "
b1 )
b1001111111110000 %
b1001111111110000 (
b111111111111 $
b111111111111 '
#450
b1010111111101111 !
b1010111111101111 *
b10100 "
b10100 )
b1001 #
b1001 &
#460
b10100 "
b10100 )
b10001 #
b10001 &
#470
b110000000010000 !
b110000000010000 *
b0 "
b0 )
b1111 #
b1111 &
#480
b111000000001111 !
b111000000001111 *
b110000000010000 +
b1010 #
b1010 &
#490
b10010 #
b10010 &
#500
b1110 #
b1110 &
#510
b10110 #
b10110 &
#520
b10100 "
b10100 )
b1001000000001111 !
b1001000000001111 *
b1011 #
b1011 &
#530
b100 "
b100 )
b10011 #
b10011 &
#540
b111111110000 !
b111111110000 *
b0 "
b0 )
b1100 #
b1100 &
#550
b10100 #
b10100 &
#560
b10100 "
b10100 )
b1001111111111111 !
b1001111111111111 *
b1101 #
b1101 &
#570
b100 "
b100 )
b10101 #
b10101 &
#580
b1111000000000000 !
b1111000000000000 *
b10100 "
b10100 )
b11001 #
b11001 &
#590
b1111000000000001 !
b1111000000000001 *
b10100 "
b10100 )
b11000 #
b11000 &
#600
b11111111111 !
b11111111111 *
b1 "
b1 )
b11010 #
b11010 &
#610
b1111111111110 !
b1111111111110 *
b0 "
b0 )
b11011 #
b11011 &
#620
b11111111111 !
b11111111111 *
b11110 #
b11110 &
#630
b1000 "
b1000 )
b0 !
b0 *
b11111 #
b11111 &
#640
b1000000000000 !
b1000000000000 *
b0 "
b0 )
b11101 #
b11101 &
#650
b1 "
b1 )
b111111111110 !
b111111111110 *
b11100 #
b11100 &
#660
b1000111111111110 !
b1000111111111110 *
b10101 "
b10101 )
b1000111111111111 $
b1000111111111111 '
#670
b10111111101111 !
b10111111101111 *
b10011 "
b10011 )
b1001 #
b1001 &
#680
b10011 "
b10011 )
b10001 #
b10001 &
#690
b110000000010000 !
b110000000010000 *
b0 "
b0 )
b1111 #
b1111 &
#700
b10100 "
b10100 )
b1111000000001111 !
b1111000000001111 *
b1010 #
b1010 &
#710
b10100 "
b10100 )
b10010 #
b10010 &
#720
b10100 "
b10100 )
b1110 #
b1110 &
#730
b10100 "
b10100 )
b10110 #
b10110 &
#740
b1000000001111 !
b1000000001111 *
b0 "
b0 )
b1011 #
b1011 &
#750
b10011 #
b10011 &
#760
b10100 "
b10100 )
b1000111111110000 !
b1000111111110000 *
b1100 #
b1100 &
#770
b100 "
b100 )
b10100 #
b10100 &
#780
b1001111111111111 !
b1001111111111111 *
b10100 "
b10100 )
b1101 #
b1101 &
#790
b100 "
b100 )
b10101 #
b10101 &
#800
b111000000000000 !
b111000000000000 *
b0 "
b0 )
b11001 #
b11001 &
#810
b111000000000001 !
b111000000000001 *
b11000 #
b11000 &
#820
b100011111111111 !
b100011111111111 *
b1 "
b1 )
b11010 #
b11010 &
#830
b1111111111110 !
b1111111111110 *
b1 "
b1 )
b11011 #
b11011 &
#840
b100011111111111 !
b100011111111111 *
b0 "
b0 )
b11110 #
b11110 &
#850
b1000 "
b1000 )
b0 !
b0 *
b11111 #
b11111 &
#860
b1001000000000000 !
b1001000000000000 *
b10100 "
b10100 )
b11101 #
b11101 &
#870
b1000111111111110 !
b1000111111111110 *
b10101 "
b10101 )
b11100 #
b11100 &
