Design/control_unit.v
/*--------------------------------------------------------------------------
    File Name :control_unit.v
    File Description :
    Project Name :
    Author Name : abhaysinh chavda
    Creation Date : 04-04-2020
    Last Modified : Tuesday 07 April 2020 12:30:05 AM IST
    Version :
    Organization : eitra        
--------------------------------------------------------------------------*/

`timescale 10ns/10ns

module control_unit(
	output reg [4:0] mem_addr,reg_addr1,reg_addr2,imd_operand,
	output reg [5:0] opcode,
	output reg [15:0] imd_addr,
	output reg mem_wr,reg_wr,IorR,PcorR,Pc_Rst,Pc_Ld,st_reg_ld,pc_addr_sel,
	output reg [1:0] Din_Sel,
	input [15:0] inst,
	input Rst,clk,
	input [4:0] flags_in);

	reg [4:0] state;
	reg M_Type,M_Type_LD;
  reg R_Type,SR_Type;
  reg B_Arth,I_Type,Imd_Arth;
  reg B_Type,B_Type_JMP,B_Type_BRZ,B_Type_BRN,B_Type_BRC,B_Type_BRV;
	reg [4:0] SrcA,DestA;


	parameter S_RESET = 5'b00000,S_FETCH = 5'b00001,S_DECODE = 5'b00010,
            S_EXEC_LD = 5'b00011, S_EXEC_ST = 5'b00100,
		        S_EXEC_B_ARTH = 5'b00101,
            S_WB = 5'b00110,S_EXEC_MOV = 5'b00111,S_WB_MOV = 5'b01000,
            S_EXEC_IMD_ARTH = 5'b01001,S_EXEC_IMD_MOV = 5'b01010,
            S_EXEC_SR = 5'b01011,
            S_INC_PC = 5'b01100, S_LD_PC = 5'b01101,
            S_PRE_FETCH = 5'b01110, S_POST_DECODE = 5'b01111,
		        S_POST_WB = 5'b10000,S_POST_EXEC_MOV = 5'b10001,
            S_EXEC_BR = 5'b10010;

	initial
		begin
		state = S_RESET;
		end

	always @(posedge clk or negedge Rst)
		if(Rst == 1'b0)
			state <= S_RESET;
		else
			case(state)
				S_RESET:
					state <= S_FETCH;
				S_FETCH:
					state <= S_DECODE;
				S_DECODE:
					state <= S_POST_DECODE;
				S_POST_DECODE:
					begin
						if(M_Type == 1'b1)  //MEMORY INSTRUCTION
							begin
							if(M_Type_LD == 1'b1)  // LOAD ( LD )
								state <= S_EXEC_LD;
							else if(M_Type_LD == 1'b0) // STORE ( ST )
								state <= S_EXEC_ST;
							end
						else if(R_Type == 1'b1) // TWO REGISTER INSTRUCTION
							begin
							if(B_Arth == 1'b1)  // FOR ARTHMETIC ( ADD,SUB,XOR,AND,SUB,OR,CMP,MUL )
								state <= S_EXEC_B_ARTH;
             					else if(B_Arth == 1'b0) // FOR MOVE ( MOV ) 
								state <= S_EXEC_MOV;
							end
						else if(I_Type == 1'b1) // IMEDIATE INSTRUCTION
							begin
							if(Imd_Arth == 1'b1) // IMEDIATE ARITHMATHIC ( ADDi,SUBi,ORi,XORi,ANDi,CMPi ) 
								state <= S_EXEC_IMD_ARTH;
							else if(Imd_Arth == 1'b0) // IMEDIATE MOVE ( MOVi )
								state <= S_EXEC_IMD_MOV;
							end
						else if(SR_Type == 1'b1) // SINGLE REGISTER INSTRUCTION
								state <= S_EXEC_SR;
						else if(B_Type == 1'b1) // BRANCH INSTRUCTION
							begin

								if(B_Type_JMP == 1'b1) // JMP
									state <= S_EXEC_BR;
								else if(B_Type_BRZ == 1'b1 && flags_in[3] == 1'b1) // BRZ
									state <= S_EXEC_BR;
								else if(B_Type_BRN == 1'b1 && flags_in[2] == 1'b1) // BRN
									state <= S_EXEC_BR;
								else if(B_Type_BRC == 1'b1 && flags_in[0] == 1'b1) // BRC
									state <= S_EXEC_BR;
								else if(B_Type_BRV == 1'b1 && flags_in[1] == 1'b1) // BRV
									state <= S_EXEC_BR;
								else
									state <= S_INC_PC;
								
							end
            end
				S_WB,S_WB_MOV:
					state <= S_POST_WB;

				S_EXEC_LD,S_EXEC_ST,S_POST_WB:
					state <= S_INC_PC;

				S_EXEC_B_ARTH,S_EXEC_IMD_ARTH,S_EXEC_SR:
					state <= S_WB;

				S_EXEC_MOV,S_EXEC_IMD_MOV:
					state <= S_POST_EXEC_MOV;

				S_POST_EXEC_MOV:
					state <= S_WB_MOV;

				S_INC_PC,S_EXEC_BR:
					state <= S_LD_PC;

				S_LD_PC:
					state <= S_PRE_FETCH;

				S_PRE_FETCH:
					state <= S_FETCH;
      
      endcase

////////////////////////////////////////////////      

	always @(posedge clk or negedge Rst)
	
			case(state)
				S_RESET:
					begin
						Pc_Rst <= 1'b0;
					end

				S_FETCH:
					begin
						Pc_Rst <= 1'b1;
          end

				S_DECODE:
					begin
						opcode <= inst[15:10];
						SrcA <= inst[4:0];
						DestA <= inst[9:5];
						imd_operand <= inst[4:0];
						imd_addr <= {6'b000000,inst[9:0]};
						{M_Type,M_Type_LD} <= 2'b00;
						R_Type <= 1'b0;	
						B_Arth <= 1'b0;
						I_Type <= 1'b0;
						Imd_Arth <= 1'b0;
						SR_Type <= 1'b0;
						B_Type <= 1'b0;
						pc_addr_sel <= 1'b0;
						{B_Type_JMP,B_Type_BRZ,B_Type_BRN,B_Type_BRC,B_Type_BRV} <= 5'b00000;
																
						if(inst[15:13] == 3'b000)
							M_Type <= 1'b1;
						
						if(inst[15:10] == 6'b000_000)
							M_Type_LD <= 1'b1;
							
						if(inst[15:13] == 3'b001)
							R_Type <= 1'b1;
						
						if(inst[15:10] != 6'b001_000)
							B_Arth <= 1'b1;

						if(inst[15:13] == 3'b010)
							I_Type <= 1'b1;
						
						if(inst[15:10] != 6'b010_000)
							Imd_Arth <= 1'b1;

						if(inst[15:13] == 3'b011)
							SR_Type <= 1'b1;
						
						if(inst[15:13] == 3'b100)
							B_Type <= 1'b1;

						if(inst[15:10] == 6'b100_000)
							B_Type_JMP <= 1'b1;

						if(inst[15:10] == 6'b100_001)
							B_Type_BRZ <= 1'b1;

						if(inst[15:10] == 6'b100_010)
							B_Type_BRN <= 1'b1;

						if(inst[15:10] == 6'b100_011)
							B_Type_BRC <= 1'b1;

						if(inst[15:10] == 6'b100_100)
							B_Type_BRV <= 1'b1;


          end

				S_EXEC_LD:
					begin
						mem_wr <= 1'b0;
						mem_addr <= SrcA;
						reg_addr1 <= DestA;
						Din_Sel <= 1'b0;
						reg_wr <= 1'b1;
					end

				S_EXEC_ST:
					begin
						mem_wr <= 1'b1;
						mem_addr <= DestA;
						reg_addr1 <= SrcA;
						reg_wr <= 1'b0;
					end

				S_EXEC_B_ARTH:
					begin
						reg_addr1 <= DestA;
						reg_addr2 <= SrcA;
						reg_wr <= 1'b0;
						IorR <= 1'b1;
						PcorR <= 1'b0;
					end

				S_EXEC_MOV:
					begin
						reg_addr1 <= DestA;
						reg_addr2 <= SrcA;
						IorR <= 1'b1;
						reg_wr <= 1'b0;
					end

				S_POST_EXEC_MOV:
					begin
						reg_wr <= 1'b0;
					end

				S_WB_MOV:
					begin
						Din_Sel = 2'b10;
						reg_wr <= 1'b1;
					end

				S_EXEC_IMD_ARTH:
					begin
						reg_addr1 = DestA;
						reg_wr <= 1'b0;
						IorR <= 1'b0;
						PcorR <= 1'b0;
					end

				S_EXEC_IMD_MOV:
					begin
						reg_addr1 <= DestA;
						IorR <= 1'b0;
						reg_wr <= 1'b0;
					end

				S_EXEC_SR:
					begin
						reg_addr1 <= SrcA;
						reg_wr <= 1'b0;
						PcorR <= 1'b0;
					end

				S_WB:
					begin
						Din_Sel <= 1'b1;
						reg_wr <= 1'b1;
						if(R_Type == 1'b1 || I_Type == 1'b1 || SR_Type == 1'b1)
							st_reg_ld <= 1'b1;
					end

				S_POST_WB:
					begin
						reg_wr <= 1'b0;
						st_reg_ld <= 1'b0;
					end

				S_INC_PC:
					begin
						PcorR <= 1'b1;
						opcode <= 6'b011_101;
						
					end

				S_LD_PC:
					begin
						Pc_Ld <= 1'b1;
					end

				S_PRE_FETCH:
					begin
						Pc_Ld <= 1'b0;
						PcorR <= 1'b0;
					end

				S_EXEC_BR:
					begin
						pc_addr_sel <= 1'b1;
          end


			endcase
		
		
endmodule

Test_Bench/control_unit_tb.v
/*--------------------------------------------------------------------------
    File Name :control_unit_tb.v
    File Description :
    Project Name :
    Author Name : abhaysinh chavda
    Creation Date : 19-03-2020
    Last Modified : Tuesday 09 June 2020 06:59:47 PM IST
    Version :
    Organization : eitra        
--------------------------------------------------------------------------*/

`timescale 10ns/10ns

module control_unit_tb();
wire [4:0] mem_addr,reg_addr1,reg_addr2,imd_operand;
wire [5:0]opcode;
wire [15:0]imd_addr;
wire mem_wr,reg_wr,IorR,PcorR,Pc_Rst,Pc_Ld,st_reg_ld,pc_addr_sel;
wire [1:0]Din_Sel;
reg [15:0]inst;
reg Rst,clk;
reg [4:0] flags_in;


control_unit m(.mem_addr,.reg_addr1,.reg_addr2,.imd_operand,.opcode,.imd_addr,.mem_wr,.reg_wr,.IorR,.PcorR,.Pc_Rst,.Pc_Ld,.st_reg_ld,.pc_addr_sel,.Din_Sel,.inst,.Rst,.clk,.flags_in);

always #10 clk=~clk;

initial begin
  $dumpfile("control_unit.vcd");
  $dumpvars;
  $monitor("mem_addr=%b reg_addr1=%b reg_addr2=%b imd_operand=%b opcode=%b imd_addr=%b mem_wr=%b reg_wr=%b IorR=%b PcorR=%b Pc_rst=%b Pc_Ld=%b st_reg_ld=%b pc_addr_sel=%b sel=%b inst=%b Rst=%b clk=%b flags_in=%b",mem_addr,reg_addr1,reg_addr2,imd_operand,opcode,imd_addr,mem_wr,reg_wr,IorR,PcorR,Pc_Rst,Pc_Ld,st_reg_ld,pc_addr_sel,Din_Sel,inst,Rst,clk,flags_in);

  inst <= 16'b000_000_00001_00000;
  Rst<=1'b1;
  clk<=1;
  flags_in<=5'b00000;

  #170 inst<=16'b001_011_00001_00000;
  //Rst<=1'b1;

  #170 inst<=16'b010_000_00001_01000;

  #170 inst<=16'b011_000_00001_00001;

  #170 inst<=16'b100_000_0000001010;

  #170 inst<=16'b101_000_00001_00010;

  #170 inst<=16'b110_000_00000_00000;

  #2000 $finish;
end

endmodule

Simulation/control_unit.vcd
$date
	Tue Jun  9 19:00:08 2020
$end
$version
	Icarus Verilog
$end
$timescale
	10ns
$end
$scope module control_unit_tb $end
$var wire 1 ! st_reg_ld $end
$var wire 1 " reg_wr $end
$var wire 5 # reg_addr2 [4:0] $end
$var wire 5 $ reg_addr1 [4:0] $end
$var wire 1 % pc_addr_sel $end
$var wire 6 & opcode [5:0] $end
$var wire 1 ' mem_wr $end
$var wire 5 ( mem_addr [4:0] $end
$var wire 5 ) imd_operand [4:0] $end
$var wire 16 * imd_addr [15:0] $end
$var wire 1 + PcorR $end
$var wire 1 , Pc_Rst $end
$var wire 1 - Pc_Ld $end
$var wire 1 . IorR $end
$var wire 2 / Din_Sel [1:0] $end
$var reg 1 0 Rst $end
$var reg 1 1 clk $end
$var reg 5 2 flags_in [4:0] $end
$var reg 16 3 inst [15:0] $end
$scope module m $end
$var wire 1 0 Rst $end
$var wire 1 1 clk $end
$var wire 5 4 flags_in [4:0] $end
$var wire 16 5 inst [15:0] $end
$var reg 1 6 B_Arth $end
$var reg 1 7 B_Type $end
$var reg 1 8 B_Type_BRC $end
$var reg 1 9 B_Type_BRN $end
$var reg 1 : B_Type_BRV $end
$var reg 1 ; B_Type_BRZ $end
$var reg 1 < B_Type_JMP $end
$var reg 5 = DestA [4:0] $end
$var reg 2 > Din_Sel [1:0] $end
$var reg 1 ? I_Type $end
$var reg 1 @ Imd_Arth $end
$var reg 1 . IorR $end
$var reg 1 A M_Type $end
$var reg 1 B M_Type_LD $end
$var reg 1 - Pc_Ld $end
$var reg 1 , Pc_Rst $end
$var reg 1 + PcorR $end
$var reg 1 C R_Type $end
$var reg 1 D SR_Type $end
$var reg 5 E SrcA [4:0] $end
$var reg 16 F imd_addr [15:0] $end
$var reg 5 G imd_operand [4:0] $end
$var reg 5 H mem_addr [4:0] $end
$var reg 1 ' mem_wr $end
$var reg 6 I opcode [5:0] $end
$var reg 1 % pc_addr_sel $end
$var reg 5 J reg_addr1 [4:0] $end
$var reg 5 K reg_addr2 [4:0] $end
$var reg 1 " reg_wr $end
$var reg 1 ! st_reg_ld $end
$var reg 5 L state [4:0] $end
$upscope $end
$upscope $end
$enddefinitions $end
#0
$dumpvars
b1 L
bx K
bx J
bx I
bx H
bx G
bx F
bx E
xD
xC
xB
xA
x@
x?
bx >
bx =
x<
x;
x:
x9
x8
x7
x6
b100000 5
b0 4
b100000 3
b0 2
11
10
bx /
x.
x-
0,
x+
bx *
bx )
bx (
x'
bx &
x%
bx $
bx #
x"
x!
$end
#10
01
#20
1,
b10 L
11
#30
01
#40
b1111 L
0<
0;
09
08
0:
0%
07
0D
1@
0?
16
0C
1A
1B
b100000 *
b100000 F
b0 )
b0 G
b1 =
b0 E
b0 &
b0 I
11
#50
01
#60
b11 L
11
#70
01
#80
b1100 L
1"
b0 /
b0 >
b1 $
b1 J
b0 (
b0 H
0'
11
#90
01
#100
b11101 &
b11101 I
1+
b1101 L
11
#110
01
#120
b1110 L
1-
11
#130
01
#140
0+
0-
b1 L
11
#150
01
#160
b10 L
11
#170
b10110000100000 3
b10110000100000 5
01
#180
1C
1@
16
0A
0B
b1011 &
b1011 I
b1111 L
11
#190
01
#200
b101 L
11
#210
01
#220
1.
0"
b0 #
b0 K
b110 L
11
#230
01
#240
b10000 L
1!
1"
b1 /
b1 >
11
#250
01
#260
0!
0"
b1100 L
11
#270
01
#280
b1101 L
b11101 &
b11101 I
1+
11
#290
01
#300
1-
b1110 L
11
#310
01
#320
b1 L
0+
0-
11
#330
01
#340
b10 L
b100000000101000 3
b100000000101000 5
11
#350
01
#360
b1111 L
1?
0@
16
0C
b101000 *
b101000 F
b1000 )
b1000 G
b1000 E
b10000 &
b10000 I
11
#370
01
#380
b1010 L
11
#390
01
#400
b10001 L
0.
11
#410
01
#420
b1000 L
11
#430
01
#440
b10000 L
1"
b10 /
b10 >
11
#450
01
#460
0"
b1100 L
11
#470
01
#480
b1101 L
b11101 &
b11101 I
1+
11
#490
01
#500
1-
b1110 L
11
#510
b110000000100001 3
b110000000100001 5
01
#520
b1 L
0+
0-
11
#530
01
#540
b10 L
11
#550
01
#560
b1111 L
1D
1@
0?
16
b100001 *
b100001 F
b1 )
b1 G
b1 E
b11000 &
b11000 I
11
#570
01
#580
b1011 L
11
#590
01
#600
b110 L
11
#610
01
#620
1!
1"
b1 /
b1 >
b10000 L
11
#630
01
#640
b1100 L
0!
0"
11
#650
01
#660
b11101 &
b11101 I
1+
b1101 L
11
#670
01
#680
b1110 L
1-
b1000000000001010 3
b1000000000001010 5
11
#690
01
#700
0+
0-
b1 L
11
#710
01
#720
b10 L
11
#730
01
#740
1<
17
0D
1@
16
b1010 *
b1010 F
b1010 )
b1010 G
b0 =
b1010 E
b100000 &
b100000 I
b1111 L
11
#750
01
#760
b10010 L
11
#770
01
#780
1%
b1101 L
11
#790
01
#800
b1110 L
1-
11
#810
01
#820
0-
b1 L
11
#830
01
#840
b10 L
11
#850
b1010000000100010 3
b1010000000100010 5
01
#860
0<
0%
07
1@
16
b100010 *
b100010 F
b10 )
b10 G
b1 =
b10 E
b101000 &
b101000 I
b1111 L
11
#870
01
#880
11
#890
01
#900
11
#910
01
#920
11
#930
01
#940
11
#950
01
#960
11
#970
01
#980
11
#990
01
#1000
11
#1010
01
#1020
b1100000000000000 3
b1100000000000000 5
11
