Design/instruction_memory.v
/*--------------------------------------------------------------------------
    File Name :instruction_memory.v
    File Description :
    Project Name :
    Author Name : abhaysinh chavda
    Creation Date : 22-03-2020
    Last Modified : Friday 03 April 2020 06:03:23 PM IST
    Version :
    Organization : eitra        
--------------------------------------------------------------------------*/

`timescale 10ns/10ns

module inst_mem(
  output reg [15:0] inst,
	input [15:0] inst_addr,
	input clk);

initial inst = 16'bzzzzzz_zzzzz_zzzzz;

always @(negedge clk)
begin
  case(inst_addr)
    		16'd0:
      			inst <= 16'b001010_00000_00001; //SUB #R0, #R1
		16'd1:
			inst <= 16'b000000_00001_00001; //LD #R1, DM[1]
		16'd2:
			inst <= 16'b000000_00000_00000; //LD #R0, DM[0]
		16'd3:
			inst <= 16'b100001_00000_00101; //BRZ 16'd5
		16'd4:
			inst <= 16'b010000_00000_00101; //MOVi #R0, 5
		16'd5:
			inst <= 16'b010000_00000_00110; //MOVi #R0, 6
		16'd6:
			inst <= 16'b000001_00010_00000; //ST DM[2], #R0

	default:
    inst <= 16'bzzzzzz_zzzzz_zzzzz;

  endcase
end
endmodule

Test_Bench/instruction_memory_tb.v
/*--------------------------------------------------------------------------
    File Name :instruction_memory_tb.v
    File Description :
    Project Name :
    Author Name : abhaysinh chavda
    Creation Date : 21-03-2020
    Last Modified : Saturday 21 March 2020 10:45:09 PM IST
    Version :
    Organization : eitra        
--------------------------------------------------------------------------*/

`timescale 10ns/10ns

module inst_mem_tb();
wire [15:0]inst;
reg [15:0]inst_addr;
reg clk;
integer i;

inst_mem m(.inst,.inst_addr,.clk);

always #10 clk=~clk;

initial begin
  $dumpfile("instruction_memory.vcd");
  $dumpvars;
  $monitor("clk=%b inst_addr=%b inst=%b",clk,inst_addr,inst);

  clk<=0;
  for(i=0;i<10;i++)
    #40 inst_addr=i;
  #50 $finish;
end

endmodule

Simulation/instruction_memory.vcd
$date
	Sat Mar 21 13:15:40 2020
$end
$version
	Icarus Verilog
$end
$timescale
	10ns
$end
$scope module inst_mem_tb $end
$var wire 16 ! inst [15:0] $end
$var reg 1 " clk $end
$var reg 16 # inst_addr [15:0] $end
$var integer 32 $ i [31:0] $end
$scope module m $end
$var wire 1 " clk $end
$var wire 16 % inst_addr [15:0] $end
$var reg 16 & inst [15:0] $end
$upscope $end
$upscope $end
$enddefinitions $end
#0
$dumpvars
bz &
bx %
b0 $
bx #
0"
bz !
$end
#10
1"
#20
0"
#30
1"
#40
b0 !
b0 &
0"
b1 $
b0 #
b0 %
#50
1"
#60
0"
#70
1"
#80
b100001 !
b100001 &
0"
b10 $
b1 #
b1 %
#90
1"
#100
0"
#110
1"
#120
b10100000000001 !
b10100000000001 &
0"
b11 $
b10 #
b10 %
#130
1"
#140
0"
#150
1"
#160
b1000010000000101 !
b1000010000000101 &
0"
b100 $
b11 #
b11 %
#170
1"
#180
0"
#190
1"
#200
b100000000000101 !
b100000000000101 &
0"
b101 $
b100 #
b100 %
#210
1"
#220
0"
#230
1"
#240
b100000000000110 !
b100000000000110 &
0"
b110 $
b101 #
b101 %
#250
1"
#260
0"
#270
1"
#280
b1100000000000000 !
b1100000000000000 &
0"
b111 $
b110 #
b110 %
#290
1"
#300
0"
#310
1"
#320
b1010000000000001 !
b1010000000000001 &
0"
b1000 $
b111 #
b111 %
#330
1"
#340
0"
#350
1"
#360
b10001000000 !
b10001000000 &
0"
b1001 $
b1000 #
b1000 %
#370
1"
#380
0"
#390
1"
#400
bz !
bz &
0"
b1010 $
b1001 #
b1001 %
