Design/status_register.v
/*--------------------------------------------------------------------------
    File Name :status_register.v
    File Description :
    Project Name :
    Author Name : abhaysinh chavda
    Creation Date : 01-03-2020
    Last Modified : Saturday 21 March 2020 10:46:28 PM IST
    Version :
    Organization :         
--------------------------------------------------------------------------*/

`timescale 10ns/10ns

module status_reg(
		output [4:0]flags_out,
		input [4:0]flags_in,
		input clk,ld,rst);

reg [4:0]st_reg;

assign flags_out = st_reg;

initial st_reg = 5'b00000;

always @(posedge clk or negedge rst)
begin
  if(rst == 1'b0)
    st_reg <= 5'b00000;
	else
		if(ld == 1'b1)
      st_reg <= flags_in;
		end

endmodule

Test_Bench/status_register_tb.v
/*--------------------------------------------------------------------------
    File Name :status_register_tb.v
    File Description :
    Project Name :
    Author Name : abhaysinh chavda
    Creation Date : 20-03-2020
    Last Modified : Saturday 21 March 2020 10:46:31 PM IST
    Version :
    Organization : eitra        
--------------------------------------------------------------------------*/

`timescale 10ns/10ns

module status_reg_tb();
wire [4:0]flags_out;
reg [4:0]flags_in;
reg clk,ld,rst;

status_reg m(.flags_out,.flags_in,.clk,.ld,.rst);

always #10 clk=~clk;

initial begin
  $dumpfile("status_register.vcd");
  $dumpvars;
  $monitor("clk=%b ld=%b rst=%b flags_in=%b flags_out=%b",clk,ld,rst,flags_in,flags_out);
  
  clk<=0;
  ld<=1;
  flags_in=5'b01010;

  #20 rst<=0;
  #30 rst<=1;
  #50 ld<=0; flags_in<=5'b10101;

  #50 ld<=1;

  #100 $finish;

end

endmodule

Simulation/status_register.vcd
$date
	Sat Mar 21 12:46:15 2020
$end
$version
	Icarus Verilog
$end
$timescale
	10ns
$end
$scope module status_reg_tb $end
$var wire 5 ! flags_out [4:0] $end
$var reg 1 " clk $end
$var reg 5 # flags_in [4:0] $end
$var reg 1 $ ld $end
$var reg 1 % rst $end
$scope module m $end
$var wire 1 " clk $end
$var wire 5 & flags_in [4:0] $end
$var wire 5 ' flags_out [4:0] $end
$var wire 1 $ ld $end
$var wire 1 % rst $end
$var reg 5 ( st_reg [4:0] $end
$upscope $end
$upscope $end
$enddefinitions $end
#0
$dumpvars
b0 (
b0 '
b1010 &
x%
1$
b1010 #
0"
b0 !
$end
#10
b1010 !
b1010 '
b1010 (
1"
#20
b0 !
b0 '
b0 (
0%
0"
#30
1"
#40
0"
#50
1%
1"
#60
0"
#70
b1010 !
b1010 '
b1010 (
1"
#80
0"
#90
1"
#100
b10101 #
b10101 &
0$
0"
#110
1"
#120
0"
#130
1"
#140
0"
#150
1$
1"
#160
0"
#170
b10101 !
b10101 '
b10101 (
1"
